FLWeb/FWeb.py
FLWeb/__init__.py
FLWeb-1.0.1.dist-info/LICENSE
FLWeb-1.0.1.dist-info/METADATA
FLWeb-1.0.1.dist-info/WHEEL
FLWeb-1.0.1.dist-info/top_level.txt
FLWeb-1.0.1.dist-info/RECORD
