Metadata-Version: 2.1
Name: FLWeb
Version: 1.0.1
Summary: Extensión para Flask
Home-page: https://github.com/nakato156/FLWeb
Author: Im_Cristina
License: MIT
Keywords: flask,extension,web,server
License-File: LICENSE
